data_process/__init__.py
data_process/collect_csv_data.py
data_process/date.py
data_process/date_range.py
data_process/decimal_helper.py
data_process/dict_helper.py
data_process/filter_date.py
data_process/green_dict.py
data_process/group_by.py
data_process/io_csv.py
data_process/io_files.py
data_process/io_json.py
data_process/io_lines.py
data_process/io_yaml.py
data_process/iter_dict.py
data_process/join.py
data_process/list_helper.py
data_process/pandas_helper.py
data_process-0.3.9.dist-info/METADATA
data_process-0.3.9.dist-info/WHEEL
data_process-0.3.9.dist-info/top_level.txt
data_process-0.3.9.dist-info/RECORD
