Metadata-Version: 2.1
Name: data-process
Version: 0.3.9
Summary: make processing 2d data more convenient
Home-page: https://github.com/weaming/data-process
Author: weaming
Author-email: garden.yuen@gmail.com
License: UNKNOWN
Project-URL: Bug Reports, https://github.com/weaming/data-process
Project-URL: Source, https://github.com/weaming/data-process
Keywords: json csv pandas
Platform: UNKNOWN
